mod77/__init__.py
mod77/a1.py
mod77/a2.py
affan-0.0.1.dist-info/LICENSE
affan-0.0.1.dist-info/METADATA
affan-0.0.1.dist-info/WHEEL
affan-0.0.1.dist-info/top_level.txt
affan-0.0.1.dist-info/RECORD
