Metadata-Version: 2.1
Name: affan
Version: 0.0.1
Summary: this is library 
Author: muhammad
Author-email: affan.mastan07@gmail.com
Classifier: Development Status :: 1 - Planning
Classifier: Intended Audience :: Developers
Classifier: Programming Language :: Python :: 3
Classifier: Operating System :: Unix
Classifier: Operating System :: MacOS :: MacOS X
Classifier: Operating System :: Microsoft :: Windows
License-File: LICENSE
